hbac_bias_detection/__init__.py
hbac_bias_detection/config.py
hbac_bias_detection/hbac_bias_detection.py
hbac_bias_detection/hbac_kmeans.py
hbac_bias_detection/hbac_utils.py
hbac_bias_detection-0.2.6.dist-info/METADATA
hbac_bias_detection-0.2.6.dist-info/WHEEL
hbac_bias_detection-0.2.6.dist-info/top_level.txt
hbac_bias_detection-0.2.6.dist-info/RECORD
